<annotation>
	<folder>kermit</folder>
	<filename>New_kermit.png</filename>
	<path>C:\Users\Мария\Desktop\kermit\New_kermit.png</path>
	<source>
		<database>Unknown</database>
	</source>
	<size>
		<width>244</width>
		<height>307</height>
		<depth>3</depth>
	</size>
	<segmented>0</segmented>
	<object>
		<name>kermit</name>
		<pose>Unspecified</pose>
		<truncated>0</truncated>
		<difficult>0</difficult>
		<bndbox>
			<xmin>67</xmin>
			<ymin>28</ymin>
			<xmax>178</xmax>
			<ymax>153</ymax>
		</bndbox>
	</object>
</annotation>
